{"type": "Image", "bands": [{"id": "B1", "data_type": {"type": "PixelType", "precision": "int", "min": 0, "max": 65535}, "dimensions": [1830, 1830], "crs": "EPSG:32632", "crs_transform": [60, 0, 300000, 0, -60, 5200020]}, {"id": "B2", "data_type": {"type": "PixelType", "precision": "int", "min": 0, "max": 65535}, "dimensions": [10980, 10980], "crs": "EPSG:32632", "crs_transform": [10, 0, 300000, 0, -10, 5200020]}, {"id": "B3", "data_type": {"type": "PixelType", "precision": "int", "min": 0, "max": 65535}, "dimensions": [10980, 10980], "crs": "EPSG:32632", "crs_transform": [10, 0, 300000, 0, -10, 5200020]}, {"id": "B4", "data_type": {"type": "PixelType", "precision": "int", "min": 0, "max": 65535}, "dimensions": [10980, 10980], "crs": "EPSG:32632", "crs_transform": [10, 0, 300000, 0, -10, 5200020]}, {"id": "B5", "data_type": {"type": "PixelType", "precision": "int", "min": 0, "max": 65535}, "dimensions": [5490, 5490], "crs": "EPSG:32632", "crs_transform": [20, 0, 300000, 0, -20, 5200020]}, {"id": "B6", "data_type": {"type": "PixelType", "precision": "int", "min": 0, "max": 65535}, "dimensions": [5490, 5490], "crs": "EPSG:32632", "crs_transform": [20, 0, 300000, 0, -20, 5200020]}, {"id": "B7", "data_type": {"type": "PixelType", "precision": "int", "min": 0, "max": 65535}, "dimensions": [5490, 5490], "crs": "EPSG:32632", "crs_transform": [20, 0, 300000, 0, -20, 5200020]}, {"id": "B8", "data_type": {"type": "PixelType", "precision": "int", "min": 0, "max": 65535}, "dimensions": [10980, 10980], "crs": "EPSG:32632", "crs_transform": [10, 0, 300000, 0, -10, 5200020]}, {"id": "B8A", "data_type": {"type": "PixelType", "precision": "int", "min": 0, "max": 65535}, "dimensions": [5490, 5490], "crs": "EPSG:32632", "crs_transform": [20, 0, 300000, 0, -20, 5200020]}, {"id": "B9", "data_type": {"type": "PixelType", "precision": "int", "min": 0, "max": 65535}, "dimensions": [1830, 1830], "crs": "EPSG:32632", "crs_transform": [60, 0, 300000, 0, -60, 5200020]}, {"id": "B11", "data_type": {"type": "PixelType", "precision": "int", "min": 0, "max": 65535}, "dimensions": [5490, 5490], "crs": "EPSG:32632", "crs_transform": [20, 0, 300000, 0, -20, 5200020]}, {"id": "B12", "data_type": {"type": "PixelType", "precision": "int", "min": 0, "max": 65535}, "dimensions": [5490, 5490], "crs": "EPSG:32632", "crs_transform": [20, 0, 300000, 0, -20, 5200020]}, {"id": "AOT", "data_type": {"type": "PixelType", "precision": "int", "min": 0, "max": 65535}, "dimensions": [10980, 10980], "crs": "EPSG:32632", "crs_transform": [10, 0, 300000, 0, -10, 5200020]}, {"id": "WVP", "data_type": {"type": "PixelType", "precision": "int", "min": 0, "max": 65535}, "dimensions": [10980, 10980], "crs": "EPSG:32632", "crs_transform": [10, 0, 300000, 0, -10, 5200020]}, {"id": "SCL", "data_type": {"type": "PixelType", "precision": "int", "min": 0, "max": 255}, "dimensions": [5490, 5490], "crs": "EPSG:32632", "crs_transform": [20, 0, 300000, 0, -20, 5200020]}, {"id": "TCI_R", "data_type": {"type": "PixelType", "precision": "int", "min": 0, "max": 255}, "dimensions": [10980, 10980], "crs": "EPSG:32632", "crs_transform": [10, 0, 300000, 0, -10, 5200020]}, {"id": "TCI_G", "data_type": {"type": "PixelType", "precision": "int", "min": 0, "max": 255}, "dimensions": [10980, 10980], "crs": "EPSG:32632", "crs_transform": [10, 0, 300000, 0, -10, 5200020]}, {"id": "TCI_B", "data_type": {"type": "PixelType", "precision": "int", "min": 0, "max": 255}, "dimensions": [10980, 10980], "crs": "EPSG:32632", "crs_transform": [10, 0, 300000, 0, -10, 5200020]}, {"id": "MSK_CLDPRB", "data_type": {"type": "PixelType", "precision": "int", "min": 0, "max": 255}, "dimensions": [5490, 5490], "crs": "EPSG:32632", "crs_transform": [20, 0, 300000, 0, -20, 5200020]}, {"id": "MSK_SNWPRB", "data_type": {"type": "PixelType", "precision": "int", "min": 0, "max": 255}, "dimensions": [5490, 5490], "crs": "EPSG:32632", "crs_transform": [20, 0, 300000, 0, -20, 5200020]}, {"id": "QA10", "data_type": {"type": "PixelType", "precision": "int", "min": 0, "max": 65535}, "dimensions": [10980, 10980], "crs": "EPSG:32632", "crs_transform": [10, 0, 300000, 0, -10, 5200020]}, {"id": "QA20", "data_type": {"type": "PixelType", "precision": "int", "min": 0, "max": 4294967295}, "dimensions": [5490, 5490], "crs": "EPSG:32632", "crs_transform": [20, 0, 300000, 0, -20, 5200020]}, {"id": "QA60", "data_type": {"type": "PixelType", "precision": "int", "min": 0, "max": 65535}, "dimensions": [1830, 1830], "crs": "EPSG:32632", "crs_transform": [60, 0, 300000, 0, -60, 5200020]}], "version": 1697840888952416, "id": "COPERNICUS/S2_SR_HARMONIZED/20231019T104041_20231019T104148_T32TLS", "properties": {"SPACECRAFT_NAME": "Sentinel-2A", "SATURATED_DEFECTIVE_PIXEL_PERCENTAGE": 0, "BOA_ADD_OFFSET_B12": -1000, "CLOUD_SHADOW_PERCENTAGE": 0.000745, "system:footprint": {"type": "LinearRing", "coordinates": [[6.410709755696245, 46.13332182081713], [6.410814389360462, 46.13323414789997], [6.411414973592105, 46.13324777036691], [6.411722846545217, 46.13347617689555], [6.521461661152974, 46.38793820325838], [6.561787314247991, 46.48114626380136], [6.585182111239264, 46.53537266642716], [6.722905825467053, 46.852467274301375], [6.743643102017696, 46.90228552129777], [6.745789790657334, 46.90745781373342], [6.7472176439804, 46.91099645959158], [6.749114065564353, 46.91589453337642], [6.752885635588363, 46.92623086900879], [6.753343843366345, 46.92786268997865], [6.754253550184781, 46.93130987570472], [6.754238106328644, 46.93167892575229], [6.754132426786399, 46.93176692030496], [6.372853745768196, 46.92364792136138], [6.3919830173167425, 46.5284565663621], [6.410709755696245, 46.13332182081713]]}, "SENSOR_QUALITY": "PASSED", "GENERATION_TIME": 1697730774000, "CLOUDY_PIXEL_OVER_LAND_PERCENTAGE": 99.998546, "CLOUD_COVERAGE_ASSESSMENT": 99.982029, "THIN_CIRRUS_PERCENTAGE": 4.553586, "GRANULE_MEAN_WV": 1.492999, "BOA_ADD_OFFSET_B1": -1000, "BOA_ADD_OFFSET_B2": -1000, "DATASTRIP_ID": "S2A_OPER_MSI_L2A_DS_2APS_20231019T155254_S20231019T104148_N05.09", "BOA_ADD_OFFSET_B5": -1000, "BOA_ADD_OFFSET_B6": -1000, "BOA_ADD_OFFSET_B3": -1000, "BOA_ADD_OFFSET_B4": -1000, "BOA_ADD_OFFSET_B9": -1000, "BOA_ADD_OFFSET_B7": -1000, "BOA_ADD_OFFSET_B8": -1000, "GRANULE_ID": "L2A_T32TLS_A043477_20231019T104148", "MEAN_INCIDENCE_AZIMUTH_ANGLE_B8": 290.584429077747, "DATATAKE_TYPE": "INS-NOBS", "MEAN_INCIDENCE_AZIMUTH_ANGLE_B9": 296.670558120075, "MEAN_INCIDENCE_AZIMUTH_ANGLE_B6": 293.933817470292, "MEAN_INCIDENCE_AZIMUTH_ANGLE_B7": 294.617555839044, "MEAN_INCIDENCE_AZIMUTH_ANGLE_B4": 292.549799010445, "NOT_VEGETATED_PERCENTAGE": 0.00021699999999999996, "MEAN_INCIDENCE_AZIMUTH_ANGLE_B5": 293.234065372465, "RADIOMETRIC_QUALITY": "PASSED", "MEAN_INCIDENCE_AZIMUTH_ANGLE_B2": 289.892264366671, "MEAN_INCIDENCE_AZIMUTH_ANGLE_B3": 291.277200361482, "MEAN_INCIDENCE_AZIMUTH_ANGLE_B1": 295.969037379526, "HIGH_PROBA_CLOUDS_PERCENTAGE": 23.314677, "UNCLASSIFIED_PERCENTAGE": 0, "OZONE_SOURCE": "AUX_ECMWFT", "GRANULE_MEAN_AOT": 0.082513, "BOA_ADD_OFFSET_B8A": -1000, "SNOW_ICE_PERCENTAGE": 0, "BOA_ADD_OFFSET_B11": -1000, "BOA_ADD_OFFSET_B10": -1000, "GEOMETRIC_QUALITY": "PASSED", "system:asset_size": 115273850, "system:index": "20231019T104041_20231019T104148_T32TLS", "DATATAKE_IDENTIFIER": "GS2A_20231019T104041_043477_N05.09", "AOT_RETRIEVAL_ACCURACY": 0, "AOT_RETRIEVAL_METHOD": "CAMS", "MEAN_INCIDENCE_AZIMUTH_ANGLE_B8A": 295.309675502538, "MEAN_SOLAR_AZIMUTH_ANGLE": 171.592150936905, "VEGETATION_PERCENTAGE": 9.3e-05, "SOLAR_IRRADIANCE_B12": 85.25, "SOLAR_IRRADIANCE_B10": 367.15, "SOLAR_IRRADIANCE_B11": 245.59, "SOLAR_IRRADIANCE_B8A": 955.32, "FORMAT_CORRECTNESS": "PASSED", "system:time_end": 1697712477362, "WATER_VAPOUR_RETRIEVAL_ACCURACY": 0, "OZONE_VALUE": 285.440879, "system:time_start": 1697712477362, "PROCESSING_BASELINE": "05.09", "SENSING_ORBIT_NUMBER": 8, "NODATA_PIXEL_PERCENTAGE": 89.309454, "SENSING_ORBIT_DIRECTION": "DESCENDING", "GENERAL_QUALITY": "PASSED", "REFLECTANCE_CONVERSION_CORRECTION": 1.0063007337144, "MEDIUM_PROBA_CLOUDS_PERCENTAGE": 72.11377, "MEAN_INCIDENCE_ZENITH_ANGLE_B1": 11.1118578573147, "MEAN_INCIDENCE_ZENITH_ANGLE_B5": 11.027382762371, "MEAN_INCIDENCE_ZENITH_ANGLE_B4": 11.0108709474206, "MEAN_INCIDENCE_ZENITH_ANGLE_B3": 10.9850113636455, "MEAN_INCIDENCE_ZENITH_ANGLE_B2": 10.9639400568507, "MEAN_INCIDENCE_ZENITH_ANGLE_B9": 11.1383318457078, "MEAN_INCIDENCE_ZENITH_ANGLE_B8": 10.9735538650713, "MEAN_INCIDENCE_ZENITH_ANGLE_B7": 11.066340724605, "DARK_FEATURES_PERCENTAGE": 0.00021699999999999996, "MEAN_INCIDENCE_ZENITH_ANGLE_B6": 11.046123723875, "MEAN_SOLAR_ZENITH_ANGLE": 56.7749176284066, "MEAN_INCIDENCE_ZENITH_ANGLE_B8A": 11.0886567416101, "RADIATIVE_TRANSFER_ACCURACY": 0, "MGRS_TILE": "32TLS", "CLOUDY_PIXEL_PERCENTAGE": 99.982029, "PRODUCT_ID": "S2A_MSIL2A_20231019T104041_N0509_R008_T32TLS_20231019T155254", "MEAN_INCIDENCE_ZENITH_ANGLE_B10": 11.0015192348859, "SOLAR_IRRADIANCE_B9": 812.92, "DEGRADED_MSI_DATA_PERCENTAGE": 0, "MEAN_INCIDENCE_ZENITH_ANGLE_B11": 11.0422204929969, "L2A_QUALITY": "PASSED", "MEAN_INCIDENCE_ZENITH_ANGLE_B12": 11.0928430287856, "SOLAR_IRRADIANCE_B6": 1287.61, "MEAN_INCIDENCE_AZIMUTH_ANGLE_B10": 292.118389333403, "SOLAR_IRRADIANCE_B5": 1424.64, "MEAN_INCIDENCE_AZIMUTH_ANGLE_B11": 293.789135559215, "SOLAR_IRRADIANCE_B8": 1041.63, "MEAN_INCIDENCE_AZIMUTH_ANGLE_B12": 295.428288252124, "SOLAR_IRRADIANCE_B7": 1162.08, "SOLAR_IRRADIANCE_B2": 1959.66, "SOLAR_IRRADIANCE_B1": 1884.69, "SOLAR_IRRADIANCE_B4": 1512.06, "SOLAR_IRRADIANCE_B3": 1823.24, "WATER_PERCENTAGE": 0.016697}}