{"type": "Image", "bands": [{"id": "B1", "data_type": {"type": "PixelType", "precision": "int", "min": 0, "max": 65535}, "dimensions": [1830, 1830], "crs": "EPSG:32632", "crs_transform": [60, 0, 600000, 0, -60, 5300040]}, {"id": "B2", "data_type": {"type": "PixelType", "precision": "int", "min": 0, "max": 65535}, "dimensions": [10980, 10980], "crs": "EPSG:32632", "crs_transform": [10, 0, 600000, 0, -10, 5300040]}, {"id": "B3", "data_type": {"type": "PixelType", "precision": "int", "min": 0, "max": 65535}, "dimensions": [10980, 10980], "crs": "EPSG:32632", "crs_transform": [10, 0, 600000, 0, -10, 5300040]}, {"id": "B4", "data_type": {"type": "PixelType", "precision": "int", "min": 0, "max": 65535}, "dimensions": [10980, 10980], "crs": "EPSG:32632", "crs_transform": [10, 0, 600000, 0, -10, 5300040]}, {"id": "B5", "data_type": {"type": "PixelType", "precision": "int", "min": 0, "max": 65535}, "dimensions": [5490, 5490], "crs": "EPSG:32632", "crs_transform": [20, 0, 600000, 0, -20, 5300040]}, {"id": "B6", "data_type": {"type": "PixelType", "precision": "int", "min": 0, "max": 65535}, "dimensions": [5490, 5490], "crs": "EPSG:32632", "crs_transform": [20, 0, 600000, 0, -20, 5300040]}, {"id": "B7", "data_type": {"type": "PixelType", "precision": "int", "min": 0, "max": 65535}, "dimensions": [5490, 5490], "crs": "EPSG:32632", "crs_transform": [20, 0, 600000, 0, -20, 5300040]}, {"id": "B8", "data_type": {"type": "PixelType", "precision": "int", "min": 0, "max": 65535}, "dimensions": [10980, 10980], "crs": "EPSG:32632", "crs_transform": [10, 0, 600000, 0, -10, 5300040]}, {"id": "B8A", "data_type": {"type": "PixelType", "precision": "int", "min": 0, "max": 65535}, "dimensions": [5490, 5490], "crs": "EPSG:32632", "crs_transform": [20, 0, 600000, 0, -20, 5300040]}, {"id": "B9", "data_type": {"type": "PixelType", "precision": "int", "min": 0, "max": 65535}, "dimensions": [1830, 1830], "crs": "EPSG:32632", "crs_transform": [60, 0, 600000, 0, -60, 5300040]}, {"id": "B11", "data_type": {"type": "PixelType", "precision": "int", "min": 0, "max": 65535}, "dimensions": [5490, 5490], "crs": "EPSG:32632", "crs_transform": [20, 0, 600000, 0, -20, 5300040]}, {"id": "B12", "data_type": {"type": "PixelType", "precision": "int", "min": 0, "max": 65535}, "dimensions": [5490, 5490], "crs": "EPSG:32632", "crs_transform": [20, 0, 600000, 0, -20, 5300040]}, {"id": "AOT", "data_type": {"type": "PixelType", "precision": "int", "min": 0, "max": 65535}, "dimensions": [10980, 10980], "crs": "EPSG:32632", "crs_transform": [10, 0, 600000, 0, -10, 5300040]}, {"id": "WVP", "data_type": {"type": "PixelType", "precision": "int", "min": 0, "max": 65535}, "dimensions": [10980, 10980], "crs": "EPSG:32632", "crs_transform": [10, 0, 600000, 0, -10, 5300040]}, {"id": "SCL", "data_type": {"type": "PixelType", "precision": "int", "min": 0, "max": 255}, "dimensions": [5490, 5490], "crs": "EPSG:32632", "crs_transform": [20, 0, 600000, 0, -20, 5300040]}, {"id": "TCI_R", "data_type": {"type": "PixelType", "precision": "int", "min": 0, "max": 255}, "dimensions": [10980, 10980], "crs": "EPSG:32632", "crs_transform": [10, 0, 600000, 0, -10, 5300040]}, {"id": "TCI_G", "data_type": {"type": "PixelType", "precision": "int", "min": 0, "max": 255}, "dimensions": [10980, 10980], "crs": "EPSG:32632", "crs_transform": [10, 0, 600000, 0, -10, 5300040]}, {"id": "TCI_B", "data_type": {"type": "PixelType", "precision": "int", "min": 0, "max": 255}, "dimensions": [10980, 10980], "crs": "EPSG:32632", "crs_transform": [10, 0, 600000, 0, -10, 5300040]}, {"id": "MSK_CLDPRB", "data_type": {"type": "PixelType", "precision": "int", "min": 0, "max": 255}, "dimensions": [5490, 5490], "crs": "EPSG:32632", "crs_transform": [20, 0, 600000, 0, -20, 5300040]}, {"id": "MSK_SNWPRB", "data_type": {"type": "PixelType", "precision": "int", "min": 0, "max": 255}, "dimensions": [5490, 5490], "crs": "EPSG:32632", "crs_transform": [20, 0, 600000, 0, -20, 5300040]}, {"id": "QA10", "data_type": {"type": "PixelType", "precision": "int", "min": 0, "max": 65535}, "dimensions": [10980, 10980], "crs": "EPSG:32632", "crs_transform": [10, 0, 600000, 0, -10, 5300040]}, {"id": "QA20", "data_type": {"type": "PixelType", "precision": "int", "min": 0, "max": 4294967295}, "dimensions": [5490, 5490], "crs": "EPSG:32632", "crs_transform": [20, 0, 600000, 0, -20, 5300040]}, {"id": "QA60", "data_type": {"type": "PixelType", "precision": "int", "min": 0, "max": 65535}, "dimensions": [1830, 1830], "crs": "EPSG:32632", "crs_transform": [60, 0, 600000, 0, -60, 5300040]}], "version": 1700519019095326, "id": "COPERNICUS/S2_SR_HARMONIZED/20231119T101311_20231119T101314_T32TPT", "properties": {"SPACECRAFT_NAME": "Sentinel-2A", "SATURATED_DEFECTIVE_PIXEL_PERCENTAGE": 0, "BOA_ADD_OFFSET_B12": -1000, "CLOUD_SHADOW_PERCENTAGE": 5.250507, "system:footprint": {"type": "LinearRing", "coordinates": [[11.750958432536844, 46.83278900707425], [11.75096329838831, 46.83280370905012], [11.776495093530782, 47.3261712072435], [11.802713778941722, 47.81947767046482], [11.802661597787589, 47.819520439898426], [11.802617710886356, 47.81956723450357], [11.802595898294124, 47.819570571589075], [10.612374062734865, 47.84246853444656], [10.612326135169658, 47.84244137893645], [10.612264555758035, 47.84243309853548], [10.612247727686675, 47.84241363579076], [10.605499280887342, 47.83170650167149], [10.52319485327717, 47.64926430981584], [10.317018663818361, 47.0730285631938], [10.311759711357224, 46.85836342342114], [10.311812095832558, 46.85832130914058], [10.311856473351884, 46.858275139820634], [10.311878056831949, 46.85827205968664], [11.75082764317817, 46.83272444981257], [11.75089008206332, 46.8327595447778], [11.750958432536844, 46.83278900707425]]}, "SENSOR_QUALITY": "PASSED", "GENERATION_TIME": 1700403361000, "CLOUDY_PIXEL_OVER_LAND_PERCENTAGE": 92.207658, "CLOUD_COVERAGE_ASSESSMENT": 92.259568, "THIN_CIRRUS_PERCENTAGE": 4.824667, "GRANULE_MEAN_WV": 0.881011, "BOA_ADD_OFFSET_B1": -1000, "BOA_ADD_OFFSET_B2": -1000, "DATASTRIP_ID": "S2A_OPER_MSI_L2A_DS_2APS_20231119T141601_S20231119T101314_N05.09", "BOA_ADD_OFFSET_B5": -1000, "BOA_ADD_OFFSET_B6": -1000, "BOA_ADD_OFFSET_B3": -1000, "BOA_ADD_OFFSET_B4": -1000, "BOA_ADD_OFFSET_B9": -1000, "BOA_ADD_OFFSET_B7": -1000, "BOA_ADD_OFFSET_B8": -1000, "GRANULE_ID": "L2A_T32TPT_A043920_20231119T101314", "MEAN_INCIDENCE_AZIMUTH_ANGLE_B8": 104.364582737561, "DATATAKE_TYPE": "INS-NOBS", "MEAN_INCIDENCE_AZIMUTH_ANGLE_B9": 104.227689469238, "MEAN_INCIDENCE_AZIMUTH_ANGLE_B6": 104.27961047823, "MEAN_INCIDENCE_AZIMUTH_ANGLE_B7": 104.306249666884, "MEAN_INCIDENCE_AZIMUTH_ANGLE_B4": 104.34303300754, "NOT_VEGETATED_PERCENTAGE": 0.123698, "MEAN_INCIDENCE_AZIMUTH_ANGLE_B5": 104.341685487687, "RADIOMETRIC_QUALITY": "PASSED", "MEAN_INCIDENCE_AZIMUTH_ANGLE_B2": 104.360131745949, "MEAN_INCIDENCE_AZIMUTH_ANGLE_B3": 104.356216628099, "MEAN_INCIDENCE_AZIMUTH_ANGLE_B1": 104.286876246893, "HIGH_PROBA_CLOUDS_PERCENTAGE": 45.025814, "UNCLASSIFIED_PERCENTAGE": 0.036048, "OZONE_SOURCE": "AUX_ECMWFT", "GRANULE_MEAN_AOT": 0.053322, "BOA_ADD_OFFSET_B8A": -1000, "SNOW_ICE_PERCENTAGE": 0.204261, "BOA_ADD_OFFSET_B11": -1000, "BOA_ADD_OFFSET_B10": -1000, "GEOMETRIC_QUALITY": "PASSED", "system:asset_size": 1287047080, "system:index": "20231119T101311_20231119T101314_T32TPT", "DATATAKE_IDENTIFIER": "GS2A_20231119T101311_043920_N05.09", "AOT_RETRIEVAL_ACCURACY": 0, "AOT_RETRIEVAL_METHOD": "CAMS", "MEAN_INCIDENCE_AZIMUTH_ANGLE_B8A": 104.288072134907, "MEAN_SOLAR_AZIMUTH_ANGLE": 168.923569714191, "VEGETATION_PERCENTAGE": 0.032448, "SOLAR_IRRADIANCE_B12": 85.25, "SOLAR_IRRADIANCE_B10": 367.15, "SOLAR_IRRADIANCE_B11": 245.59, "SOLAR_IRRADIANCE_B8A": 955.32, "FORMAT_CORRECTNESS": "PASSED", "system:time_end": 1700389062061, "WATER_VAPOUR_RETRIEVAL_ACCURACY": 0, "OZONE_VALUE": 260.486471, "system:time_start": 1700389062061, "PROCESSING_BASELINE": "05.09", "SENSING_ORBIT_NUMBER": 22, "NODATA_PIXEL_PERCENTAGE": 8.383778, "SENSING_ORBIT_DIRECTION": "DESCENDING", "GENERAL_QUALITY": "PASSED", "REFLECTANCE_CONVERSION_CORRECTION": 1.02247012719674, "MEDIUM_PROBA_CLOUDS_PERCENTAGE": 42.409089, "MEAN_INCIDENCE_ZENITH_ANGLE_B1": 8.00618816245737, "MEAN_INCIDENCE_ZENITH_ANGLE_B5": 7.89604763943195, "MEAN_INCIDENCE_ZENITH_ANGLE_B4": 7.87339990862087, "MEAN_INCIDENCE_ZENITH_ANGLE_B3": 7.83511700041834, "MEAN_INCIDENCE_ZENITH_ANGLE_B2": 7.80058741796187, "MEAN_INCIDENCE_ZENITH_ANGLE_B9": 8.04662829259533, "MEAN_INCIDENCE_ZENITH_ANGLE_B8": 7.82030617390469, "MEAN_INCIDENCE_ZENITH_ANGLE_B7": 7.94956401657442, "DARK_FEATURES_PERCENTAGE": 2.072102, "MEAN_INCIDENCE_ZENITH_ANGLE_B6": 7.91762847381089, "MEAN_SOLAR_ZENITH_ANGLE": 67.4986669665473, "MEAN_INCIDENCE_ZENITH_ANGLE_B8A": 7.98002191108637, "RADIATIVE_TRANSFER_ACCURACY": 0, "MGRS_TILE": "32TPT", "CLOUDY_PIXEL_PERCENTAGE": 92.259568, "PRODUCT_ID": "S2A_MSIL2A_20231119T101311_N0509_R022_T32TPT_20231119T141601", "MEAN_INCIDENCE_ZENITH_ANGLE_B10": 7.84484849866131, "SOLAR_IRRADIANCE_B9": 812.92, "DEGRADED_MSI_DATA_PERCENTAGE": 0.0123, "MEAN_INCIDENCE_ZENITH_ANGLE_B11": 7.89610055127421, "L2A_QUALITY": "PASSED", "MEAN_INCIDENCE_ZENITH_ANGLE_B12": 7.96271485808144, "SOLAR_IRRADIANCE_B6": 1287.61, "MEAN_INCIDENCE_AZIMUTH_ANGLE_B10": 104.404442796617, "SOLAR_IRRADIANCE_B5": 1424.64, "MEAN_INCIDENCE_AZIMUTH_ANGLE_B11": 104.327941140969, "SOLAR_IRRADIANCE_B8": 1041.63, "MEAN_INCIDENCE_AZIMUTH_ANGLE_B12": 104.258235555388, "SOLAR_IRRADIANCE_B7": 1162.08, "SOLAR_IRRADIANCE_B2": 1959.66, "SOLAR_IRRADIANCE_B1": 1884.69, "SOLAR_IRRADIANCE_B4": 1512.06, "SOLAR_IRRADIANCE_B3": 1823.24, "WATER_PERCENTAGE": 0.02137}}