{"type": "Image", "bands": [{"id": "B1", "data_type": {"type": "PixelType", "precision": "int", "min": 0, "max": 65535}, "dimensions": [1830, 1830], "crs": "EPSG:32632", "crs_transform": [60, 0, 300000, 0, -60, 5300040]}, {"id": "B2", "data_type": {"type": "PixelType", "precision": "int", "min": 0, "max": 65535}, "dimensions": [10980, 10980], "crs": "EPSG:32632", "crs_transform": [10, 0, 300000, 0, -10, 5300040]}, {"id": "B3", "data_type": {"type": "PixelType", "precision": "int", "min": 0, "max": 65535}, "dimensions": [10980, 10980], "crs": "EPSG:32632", "crs_transform": [10, 0, 300000, 0, -10, 5300040]}, {"id": "B4", "data_type": {"type": "PixelType", "precision": "int", "min": 0, "max": 65535}, "dimensions": [10980, 10980], "crs": "EPSG:32632", "crs_transform": [10, 0, 300000, 0, -10, 5300040]}, {"id": "B5", "data_type": {"type": "PixelType", "precision": "int", "min": 0, "max": 65535}, "dimensions": [5490, 5490], "crs": "EPSG:32632", "crs_transform": [20, 0, 300000, 0, -20, 5300040]}, {"id": "B6", "data_type": {"type": "PixelType", "precision": "int", "min": 0, "max": 65535}, "dimensions": [5490, 5490], "crs": "EPSG:32632", "crs_transform": [20, 0, 300000, 0, -20, 5300040]}, {"id": "B7", "data_type": {"type": "PixelType", "precision": "int", "min": 0, "max": 65535}, "dimensions": [5490, 5490], "crs": "EPSG:32632", "crs_transform": [20, 0, 300000, 0, -20, 5300040]}, {"id": "B8", "data_type": {"type": "PixelType", "precision": "int", "min": 0, "max": 65535}, "dimensions": [10980, 10980], "crs": "EPSG:32632", "crs_transform": [10, 0, 300000, 0, -10, 5300040]}, {"id": "B8A", "data_type": {"type": "PixelType", "precision": "int", "min": 0, "max": 65535}, "dimensions": [5490, 5490], "crs": "EPSG:32632", "crs_transform": [20, 0, 300000, 0, -20, 5300040]}, {"id": "B9", "data_type": {"type": "PixelType", "precision": "int", "min": 0, "max": 65535}, "dimensions": [1830, 1830], "crs": "EPSG:32632", "crs_transform": [60, 0, 300000, 0, -60, 5300040]}, {"id": "B11", "data_type": {"type": "PixelType", "precision": "int", "min": 0, "max": 65535}, "dimensions": [5490, 5490], "crs": "EPSG:32632", "crs_transform": [20, 0, 300000, 0, -20, 5300040]}, {"id": "B12", "data_type": {"type": "PixelType", "precision": "int", "min": 0, "max": 65535}, "dimensions": [5490, 5490], "crs": "EPSG:32632", "crs_transform": [20, 0, 300000, 0, -20, 5300040]}, {"id": "AOT", "data_type": {"type": "PixelType", "precision": "int", "min": 0, "max": 65535}, "dimensions": [10980, 10980], "crs": "EPSG:32632", "crs_transform": [10, 0, 300000, 0, -10, 5300040]}, {"id": "WVP", "data_type": {"type": "PixelType", "precision": "int", "min": 0, "max": 65535}, "dimensions": [10980, 10980], "crs": "EPSG:32632", "crs_transform": [10, 0, 300000, 0, -10, 5300040]}, {"id": "SCL", "data_type": {"type": "PixelType", "precision": "int", "min": 0, "max": 255}, "dimensions": [5490, 5490], "crs": "EPSG:32632", "crs_transform": [20, 0, 300000, 0, -20, 5300040]}, {"id": "TCI_R", "data_type": {"type": "PixelType", "precision": "int", "min": 0, "max": 255}, "dimensions": [10980, 10980], "crs": "EPSG:32632", "crs_transform": [10, 0, 300000, 0, -10, 5300040]}, {"id": "TCI_G", "data_type": {"type": "PixelType", "precision": "int", "min": 0, "max": 255}, "dimensions": [10980, 10980], "crs": "EPSG:32632", "crs_transform": [10, 0, 300000, 0, -10, 5300040]}, {"id": "TCI_B", "data_type": {"type": "PixelType", "precision": "int", "min": 0, "max": 255}, "dimensions": [10980, 10980], "crs": "EPSG:32632", "crs_transform": [10, 0, 300000, 0, -10, 5300040]}, {"id": "MSK_CLDPRB", "data_type": {"type": "PixelType", "precision": "int", "min": 0, "max": 255}, "dimensions": [5490, 5490], "crs": "EPSG:32632", "crs_transform": [20, 0, 300000, 0, -20, 5300040]}, {"id": "MSK_SNWPRB", "data_type": {"type": "PixelType", "precision": "int", "min": 0, "max": 255}, "dimensions": [5490, 5490], "crs": "EPSG:32632", "crs_transform": [20, 0, 300000, 0, -20, 5300040]}, {"id": "QA10", "data_type": {"type": "PixelType", "precision": "int", "min": 0, "max": 65535}, "dimensions": [10980, 10980], "crs": "EPSG:32632", "crs_transform": [10, 0, 300000, 0, -10, 5300040]}, {"id": "QA20", "data_type": {"type": "PixelType", "precision": "int", "min": 0, "max": 4294967295}, "dimensions": [5490, 5490], "crs": "EPSG:32632", "crs_transform": [20, 0, 300000, 0, -20, 5300040]}, {"id": "QA60", "data_type": {"type": "PixelType", "precision": "int", "min": 0, "max": 65535}, "dimensions": [1830, 1830], "crs": "EPSG:32632", "crs_transform": [60, 0, 300000, 0, -60, 5300040]}], "version": 1694989648056541, "id": "COPERNICUS/S2_SR_HARMONIZED/20230916T102651_20230916T103416_T32TLT", "properties": {"SPACECRAFT_NAME": "Sentinel-2A", "SATURATED_DEFECTIVE_PIXEL_PERCENTAGE": 0, "BOA_ADD_OFFSET_B12": -1000, "CLOUD_SHADOW_PERCENTAGE": 0.619397, "system:footprint": {"type": "LinearRing", "coordinates": [[7.794102394364787, 47.84745778831004], [7.794085652686357, 47.84745832185396], [6.32792210384278, 47.82268503631156], [6.3278623126302, 47.82264711428837], [6.327795863152536, 47.82261447593295], [6.32779244384727, 47.82259953758004], [6.35279420709639, 47.32923254560421], [6.377140153048096, 46.83582046542497], [6.377195599991114, 46.83578026835062], [6.377243226369047, 46.8357356095694], [6.377265004724537, 46.83573328188062], [7.816384207530976, 46.85967030118706], [7.816443996365216, 46.85970749360689], [7.81651015342463, 46.85973933997252], [7.8165139461162525, 46.859754107388554], [7.805515978991264, 47.35358804842255], [7.794221815072589, 47.847369738132585], [7.79416635693379, 47.84741066818919], [7.7941189291704855, 47.84745582821442], [7.794102394364787, 47.84745778831004]]}, "SENSOR_QUALITY": "PASSED", "GENERATION_TIME": 1694882816000, "CLOUDY_PIXEL_OVER_LAND_PERCENTAGE": 57.344043, "CLOUD_COVERAGE_ASSESSMENT": 57.284957, "THIN_CIRRUS_PERCENTAGE": 3.2179749999999996, "GRANULE_MEAN_WV": 2.056324, "BOA_ADD_OFFSET_B1": -1000, "BOA_ADD_OFFSET_B2": -1000, "DATASTRIP_ID": "S2A_OPER_MSI_L2A_DS_2APS_20230916T164656_S20230916T103416_N05.09", "BOA_ADD_OFFSET_B5": -1000, "BOA_ADD_OFFSET_B6": -1000, "BOA_ADD_OFFSET_B3": -1000, "BOA_ADD_OFFSET_B4": -1000, "BOA_ADD_OFFSET_B9": -1000, "BOA_ADD_OFFSET_B7": -1000, "BOA_ADD_OFFSET_B8": -1000, "GRANULE_ID": "L2A_T32TLT_A043005_20230916T103416", "MEAN_INCIDENCE_AZIMUTH_ANGLE_B8": 141.408499570647, "DATATAKE_TYPE": "INS-NOBS", "MEAN_INCIDENCE_AZIMUTH_ANGLE_B9": 135.918095344548, "MEAN_INCIDENCE_AZIMUTH_ANGLE_B6": 137.377468091737, "MEAN_INCIDENCE_AZIMUTH_ANGLE_B7": 136.918190268507, "MEAN_INCIDENCE_AZIMUTH_ANGLE_B4": 138.591463887231, "NOT_VEGETATED_PERCENTAGE": 6.214753999999999, "MEAN_INCIDENCE_AZIMUTH_ANGLE_B5": 137.932155254248, "RADIOMETRIC_QUALITY": "PASSED", "MEAN_INCIDENCE_AZIMUTH_ANGLE_B2": 142.921502853988, "MEAN_INCIDENCE_AZIMUTH_ANGLE_B3": 140.519763923646, "MEAN_INCIDENCE_AZIMUTH_ANGLE_B1": 136.023575919172, "HIGH_PROBA_CLOUDS_PERCENTAGE": 42.71867, "UNCLASSIFIED_PERCENTAGE": 1.935654, "OZONE_SOURCE": "AUX_ECMWFT", "GRANULE_MEAN_AOT": 0.082752, "BOA_ADD_OFFSET_B8A": -1000, "SNOW_ICE_PERCENTAGE": 8e-05, "BOA_ADD_OFFSET_B11": -1000, "BOA_ADD_OFFSET_B10": -1000, "GEOMETRIC_QUALITY": "PASSED", "system:asset_size": 1600480960, "system:index": "20230916T102651_20230916T103416_T32TLT", "DATATAKE_IDENTIFIER": "GS2A_20230916T102651_043005_N05.09", "AOT_RETRIEVAL_ACCURACY": 0, "AOT_RETRIEVAL_METHOD": "SEN2COR_DDV", "MEAN_INCIDENCE_AZIMUTH_ANGLE_B8A": 136.529614261221, "MEAN_SOLAR_AZIMUTH_ANGLE": 162.933806873211, "VEGETATION_PERCENTAGE": 32.973924, "SOLAR_IRRADIANCE_B12": 85.25, "SOLAR_IRRADIANCE_B10": 367.15, "SOLAR_IRRADIANCE_B11": 245.59, "SOLAR_IRRADIANCE_B8A": 955.32, "FORMAT_CORRECTNESS": "PASSED", "system:time_end": 1694860673798, "WATER_VAPOUR_RETRIEVAL_ACCURACY": 0, "OZONE_VALUE": 287.667368, "system:time_start": 1694860673798, "PROCESSING_BASELINE": "05.09", "SENSING_ORBIT_NUMBER": 108, "NODATA_PIXEL_PERCENTAGE": 3e-06, "SENSING_ORBIT_DIRECTION": "DESCENDING", "GENERAL_QUALITY": "PASSED", "REFLECTANCE_CONVERSION_CORRECTION": 0.987727097407665, "MEDIUM_PROBA_CLOUDS_PERCENTAGE": 11.348317, "MEAN_INCIDENCE_ZENITH_ANGLE_B1": 3.46036672071927, "MEAN_INCIDENCE_ZENITH_ANGLE_B5": 3.13234631976342, "MEAN_INCIDENCE_ZENITH_ANGLE_B4": 3.06107819485332, "MEAN_INCIDENCE_ZENITH_ANGLE_B3": 2.94136028914927, "MEAN_INCIDENCE_ZENITH_ANGLE_B2": 2.83909961905861, "MEAN_INCIDENCE_ZENITH_ANGLE_B9": 3.55056256353849, "MEAN_INCIDENCE_ZENITH_ANGLE_B8": 2.8870592876386, "MEAN_INCIDENCE_ZENITH_ANGLE_B7": 3.28737342413604, "DARK_FEATURES_PERCENTAGE": 0.003713, "MEAN_INCIDENCE_ZENITH_ANGLE_B6": 3.20774070275184, "MEAN_SOLAR_ZENITH_ANGLE": 45.9230648575716, "MEAN_INCIDENCE_ZENITH_ANGLE_B8A": 3.37025924922435, "RADIATIVE_TRANSFER_ACCURACY": 0, "MGRS_TILE": "32TLT", "CLOUDY_PIXEL_PERCENTAGE": 57.284957, "PRODUCT_ID": "S2A_MSIL2A_20230916T102651_N0509_R108_T32TLT_20230916T164656", "MEAN_INCIDENCE_ZENITH_ANGLE_B10": 3.02754399433245, "SOLAR_IRRADIANCE_B9": 812.92, "DEGRADED_MSI_DATA_PERCENTAGE": 0.0011, "MEAN_INCIDENCE_ZENITH_ANGLE_B11": 3.19720944442553, "L2A_QUALITY": "PASSED", "MEAN_INCIDENCE_ZENITH_ANGLE_B12": 3.39095637714152, "SOLAR_IRRADIANCE_B6": 1287.61, "MEAN_INCIDENCE_AZIMUTH_ANGLE_B10": 138.526461551152, "SOLAR_IRRADIANCE_B5": 1424.64, "MEAN_INCIDENCE_AZIMUTH_ANGLE_B11": 137.140020825919, "SOLAR_IRRADIANCE_B8": 1041.63, "MEAN_INCIDENCE_AZIMUTH_ANGLE_B12": 136.116967164685, "SOLAR_IRRADIANCE_B7": 1162.08, "SOLAR_IRRADIANCE_B2": 1959.66, "SOLAR_IRRADIANCE_B1": 1884.69, "SOLAR_IRRADIANCE_B4": 1512.06, "SOLAR_IRRADIANCE_B3": 1823.24, "WATER_PERCENTAGE": 0.967512}}